bisi/__init__.py
bisi/__version__.py
bisi/utils.py
bisi/cli/__init__.py
bisi/cli/main.py
bisi/interface/__init__.py
bisi/interface/build.py
bisi/interface/deploy.py
bisi/interface/run.py
bisi/providers/__init__.py
bisi/providers/aws.py
bisi/providers/local.py
bisi/providers/provider.py
bisi/resources/__init__.py
bisi/resources/collect.py
bisi/resources/dockerfile.py
bisi/resources/job.py
bisi/resources/resource.py
bisi/resources/config/__init__.py
bisi/resources/config/batch_job_config.py
bisi/resources/config/ecr_config.py
bisi/resources/config/local_job_config.py
bisi-0.0.3.dist-info/LICENSE
bisi-0.0.3.dist-info/METADATA
bisi-0.0.3.dist-info/WHEEL
bisi-0.0.3.dist-info/entry_points.txt
bisi-0.0.3.dist-info/top_level.txt
bisi-0.0.3.dist-info/RECORD
