Metadata-Version: 2.1
Name: bisi
Version: 0.0.3
Summary: A Python based runner for docker images.
License: UNKNOWN
Platform: UNKNOWN
Requires-Python: >=3.6.0
License-File: LICENSE
Requires-Dist: PyYAML
Requires-Dist: click
Requires-Dist: GitPython
Requires-Dist: docker
Requires-Dist: botocore
Requires-Dist: boto3
Provides-Extra: dev
Requires-Dist: pytest (==6.2.4) ; extra == 'dev'
Requires-Dist: pytest-cov ; extra == 'dev'
Requires-Dist: bump2version (==1.0.1) ; extra == 'dev'
Requires-Dist: awscli ; extra == 'dev'
Requires-Dist: build ; extra == 'dev'
Requires-Dist: twine ; extra == 'dev'
